prairiedog/__init__.py
prairiedog/cli.py
prairiedog/config.py
prairiedog/dgraph.py
prairiedog/dgraph_bundled.py
prairiedog/dgraph_bundled_helper.py
prairiedog/edge.py
prairiedog/errors.py
prairiedog/graph.py
prairiedog/graph_ref.py
prairiedog/gref.py
prairiedog/kmers.py
prairiedog/lemon_graph.py
prairiedog/logger.py
prairiedog/networkx_graph.py
prairiedog/node.py
prairiedog/prairiedog.py
prairiedog/pretty_hits.py
prairiedog/profiler.py
prairiedog/subgraph_ref.py
prairiedog-0.2.0.dist-info/AUTHORS.rst
prairiedog-0.2.0.dist-info/LICENSE
prairiedog-0.2.0.dist-info/METADATA
prairiedog-0.2.0.dist-info/WHEEL
prairiedog-0.2.0.dist-info/entry_points.txt
prairiedog-0.2.0.dist-info/top_level.txt
prairiedog-0.2.0.dist-info/RECORD
