Metadata-Version: 2.1
Name: prairiedog
Version: 0.2.0
Summary: Graphing bacterial genomes for fun and profit
Home-page: https://github.com/kevinkle/prairiedog
Author: Kevin Le
Author-email: kevin.kent.le@gmail.com
License: Apache Software License 2.0
Keywords: prairiedog
Platform: UNKNOWN
Classifier: Development Status :: 2 - Pre-Alpha
Classifier: Intended Audience :: Developers
Classifier: License :: OSI Approved :: Apache Software License
Classifier: Natural Language :: English
Classifier: Programming Language :: Python :: 3.5
Classifier: Programming Language :: Python :: 3.6
Classifier: Programming Language :: Python :: 3.7
Requires-Dist: coloredlogs (==10.0)
Requires-Dist: decorator (==4.4.0)
Requires-Dist: humanfriendly (==4.18)
Requires-Dist: networkx (==2.3)
Requires-Dist: cython
Requires-Dist: dateutils
Requires-Dist: numpy
Requires-Dist: pandas (<=0.24.2)
Requires-Dist: click (>=6.0)
Requires-Dist: dill
Requires-Dist: psutil
Requires-Dist: pyinstrument
Requires-Dist: pydgraph
Requires-Dist: snakemake
